examples/document_loader_example.py
examples/embeddings_example.py
examples/reranker_example.py
examples/retriever_example.py
mixedbread_ai_langchain/__init__.py
mixedbread_ai_langchain/py.typed
mixedbread_ai_langchain/compressors/__init__.py
mixedbread_ai_langchain/compressors/reranker.py
mixedbread_ai_langchain/embedders/__init__.py
mixedbread_ai_langchain/embedders/embeddings.py
mixedbread_ai_langchain/loaders/__init__.py
mixedbread_ai_langchain/loaders/document_loaders.py
mixedbread_ai_langchain/retrievers/__init__.py
mixedbread_ai_langchain/retrievers/vector_store_retriever.py
mixedbread_ai_langchain-1.0.2.dist-info/licenses/LICENSE
tests/__init__.py
tests/test_document_loader.py
tests/test_embeddings.py
tests/test_reranker.py
tests/test_retriever.py
mixedbread_ai_langchain-1.0.2.dist-info/METADATA
mixedbread_ai_langchain-1.0.2.dist-info/WHEEL
mixedbread_ai_langchain-1.0.2.dist-info/top_level.txt
mixedbread_ai_langchain-1.0.2.dist-info/RECORD
