Metadata-Version: 2.4
Name: mixedbread-ai-langchain
Version: 1.0.2
Summary: The official Mixedbread AI integration for LangChain.
Author-email: Mixedbread AI <support@mixedbread.com>
License: Apache-2.0
Project-URL: Homepage, https://github.com/mixedbread-ai/mixedbread-ai-langchain
Project-URL: Documentation, https://www.mixedbread.com/api-reference/integrations/langchain
Project-URL: Issues, https://github.com/mixedbread-ai/mixedbread-ai-langchain/issues
Project-URL: Source, https://github.com/mixedbread-ai/mixedbread-ai-langchain
Keywords: langchain,mixedbread-ai,embedding,reranking,document-loader,document-parser,retrieval,nlp,llm,rag
Classifier: Intended Audience :: Developers
Classifier: Programming Language :: Python
Classifier: Programming Language :: Python :: 3.9
Classifier: Programming Language :: Python :: 3.10
Classifier: Programming Language :: Python :: 3.11
Classifier: Programming Language :: Python :: 3.12
Classifier: Topic :: Software Development :: Libraries :: Python Modules
Classifier: Typing :: Typed
Requires-Python: >=3.9
License-File: LICENSE
Requires-Dist: langchain-core>=0.3.61
Requires-Dist: mixedbread>=0.8.1
Requires-Dist: pydantic>=2.0.0
Provides-Extra: dev
Requires-Dist: pytest>=7.0; extra == "dev"
Requires-Dist: pytest-asyncio>=0.20.0; extra == "dev"
Dynamic: license-file
